qdarktheme/__init__.py
qdarktheme/_color.py
qdarktheme/_icon/__init__.py
qdarktheme/_icon/icon_engine.py
qdarktheme/_icon/svg.py
qdarktheme/_main.py
qdarktheme/_os_appearance/__init__.py
qdarktheme/_os_appearance/_accent/__init__.py
qdarktheme/_os_appearance/_accent/_mac_detect.py
qdarktheme/_os_appearance/listener.py
qdarktheme/_proxy_style.py
qdarktheme/_resources/__init__.py
qdarktheme/_resources/colors.py
qdarktheme/_resources/palette.py
qdarktheme/_resources/standard_icons.py
qdarktheme/_resources/stylesheets.py
qdarktheme/_resources/svg.py
qdarktheme/_style_loader.py
qdarktheme/_template/__init__.py
qdarktheme/_template/engine.py
qdarktheme/_template/filter.py
qdarktheme/_util.py
qdarktheme/qtpy/QtCore/__init__.py
qdarktheme/qtpy/QtGui/__init__.py
qdarktheme/qtpy/QtSvg/__init__.py
qdarktheme/qtpy/QtWidgets/__init__.py
qdarktheme/qtpy/__init__.py
qdarktheme/qtpy/qt_compat.py
qdarktheme/qtpy/qt_version.py
qdarktheme/widget_gallery/__init__.py
qdarktheme/widget_gallery/__main__.py
qdarktheme/widget_gallery/_ui/__init__.py
qdarktheme/widget_gallery/_ui/dock_ui.py
qdarktheme/widget_gallery/_ui/frame_ui.py
qdarktheme/widget_gallery/_ui/icons_ui.py
qdarktheme/widget_gallery/_ui/mdi_ui.py
qdarktheme/widget_gallery/_ui/widgets_ui.py
qdarktheme/widget_gallery/main_window.py
qdarktheme/widget_gallery/svg/announcement_24dp.svg
qdarktheme/widget_gallery/svg/branding_watermark_24dp.svg
qdarktheme/widget_gallery/svg/circle_24dp.svg
qdarktheme/widget_gallery/svg/clear_24dp.svg
qdarktheme/widget_gallery/svg/contrast_24dp.svg
qdarktheme/widget_gallery/svg/crop_din_24dp.svg
qdarktheme/widget_gallery/svg/favorite_border_24dp.svg
qdarktheme/widget_gallery/svg/flip_to_front_24dp.svg
qdarktheme/widget_gallery/svg/folder_open_24dp.svg
qdarktheme/widget_gallery/svg/font_download_24dp.svg
qdarktheme/widget_gallery/svg/image_24dp.svg
qdarktheme/widget_gallery/svg/palette_24dp.svg
qdarktheme/widget_gallery/svg/settings_24dp.svg
qdarktheme/widget_gallery/svg/widgets_24dp.svg
pyqtdarkthemecglb-2.1.0.dist-info/METADATA
pyqtdarkthemecglb-2.1.0.dist-info/WHEEL
pyqtdarkthemecglb-2.1.0.dist-info/RECORD
