Metadata-Version: 2.1
Name: PyQtDarkThemeCglb
Version: 2.1.0
Summary: Flat dark theme for PySide and PyQt.
Home-page: https://github.com/5yutan5/PyQtDarkTheme
License: MIT
Keywords: qt,stylesheets,dark-theme
Author: Yunosuke Ohsugi
Author-email: 63651161+5yutan5@users.noreply.github.com
Requires-Python: >=3.7
Classifier: License :: OSI Approved :: MIT License
Classifier: Programming Language :: Python :: 3
Classifier: Programming Language :: Python :: 3.7
Classifier: Programming Language :: Python :: 3.8
Classifier: Programming Language :: Python :: 3.9
Classifier: Programming Language :: Python :: 3.10
Classifier: Programming Language :: Python :: 3.11
Classifier: Programming Language :: Python :: 3.12
Classifier: Programming Language :: Python :: 3.13
Requires-Dist: darkdetect (>=0.7.1,<0.8.0)
Project-URL: Documentation, https://pyqtdarktheme.readthedocs.io
Project-URL: Repository, https://github.com/5yutan5/PyQtDarkTheme
